QtGraphVisuals/.__main__.py.swp
QtGraphVisuals/.converters.py.swp
QtGraphVisuals/.gitignore
QtGraphVisuals/.graphic_items.py.swp
QtGraphVisuals/.properties_viewer.py.swp
QtGraphVisuals/.widgets.py.swp
QtGraphVisuals/README.md
QtGraphVisuals/__init__.py
QtGraphVisuals/__main__.py
QtGraphVisuals/converters.py
QtGraphVisuals/graphic_items.py
QtGraphVisuals/properties_viewer.py
QtGraphVisuals/widgets.py
QtGraphVisuals/icons/arrow_circle_down_FILL0_wght300_GRAD0_opsz24.svg
QtGraphVisuals/icons/arrow_circle_right_FILL0_wght300_GRAD0_opsz24.svg
QtGraphVisuals/icons/restart_alt_FILL0_wght300_GRAD0_opsz24.svg
QtGraphVisuals/icons/shape_line_FILL0_wght300_GRAD0_opsz24.svg
QtGraphVisuals/icons/subtitles_FILL0_wght300_GRAD0_opsz24.svg
QtGraphVisuals/icons/subtitles_off_FILL0_wght300_GRAD0_opsz24.svg
QtGraphVisuals/icons/zoom_out_map_FILL0_wght300_GRAD0_opsz24.svg
qtgraphvisuals-0.0.8.dist-info/METADATA
qtgraphvisuals-0.0.8.dist-info/WHEEL
qtgraphvisuals-0.0.8.dist-info/licenses/LICENSE
qtgraphvisuals-0.0.8.dist-info/RECORD
