Metadata-Version: 2.1
Name: QtGraphVisuals
Version: 0.0.8
Summary: A qt-widget to visualize directed graphs
Project-URL: Homepage, https://github.com/jake987654321/QtGraphVisuals
Project-URL: Bug Tracker, https://github.com/jake987654321/QtGraphVisuals/issues
Author-email: Jacob Botimer <botimerj@gmail.com>
License-File: LICENSE
Classifier: License :: OSI Approved :: MIT License
Classifier: Operating System :: OS Independent
Classifier: Programming Language :: Python :: 3
Requires-Python: >=3.7
Requires-Dist: networkx
Requires-Dist: numpy
Requires-Dist: pyside6
Requires-Dist: qt-material
